MANIFEST.in
README.rst
setup.cfg
setup.py
pypygo/__init__.py
pypygo/main.py
pypygo/models.py
pypygo.egg-info/PKG-INFO
pypygo.egg-info/SOURCES.txt
pypygo.egg-info/dependency_links.txt
pypygo.egg-info/requires.txt
pypygo.egg-info/top_level.txt