Metadata-Version: 1.1
Name: pypygo
Version: 0.1.0
Summary: A Python wrapper for the DuckDuckGo instant answer API
Home-page: https://github.com/ScreenDriver/pypygo
Author: RaspberryRice
Author-email: christian@echooff.de
License: MIT
Keywords: duckduckgo ddg ddgo search engine privacy
Platform: UNKNOWN
Classifier: Development Status :: 3 - Alpha
Classifier: Intended Audience :: Developers
Classifier: License :: OSI Approved :: MIT License
Classifier: Programming Language :: Python :: 3.3
Classifier: Programming Language :: Python :: 3.4
Classifier: Topic :: Internet :: WWW/HTTP :: Indexing/Search
Classifier: Topic :: Software Development :: Libraries :: Python Modules
